.travis.yml
Makefile
README.rst
bootstrap.py
buildout.cfg
setup.cfg
setup.py
travis.cfg
collective/__init__.py
collective.jbot.egg-info/PKG-INFO
collective.jbot.egg-info/SOURCES.txt
collective.jbot.egg-info/dependency_links.txt
collective.jbot.egg-info/entry_points.txt
collective.jbot.egg-info/namespace_packages.txt
collective.jbot.egg-info/not-zip-safe
collective.jbot.egg-info/requires.txt
collective.jbot.egg-info/top_level.txt
collective/jbot/__init__.py
collective/jbot/configure.zcml
collective/jbot/editor.pt
collective/jbot/interfaces.py
collective/jbot/manager.py
collective/jbot/resource.py
collective/jbot/setuphandlers.py
collective/jbot/testing.py
collective/jbot/views.py
collective/jbot/profiles/default/browserlayer.xml
collective/jbot/profiles/default/controlpanel.xml
collective/jbot/profiles/default/import_steps.xml
collective/jbot/profiles/default/metadata.xml
collective/jbot/tests/__init__.py
collective/jbot/tests/test_manager.py
collective/jbot/tests/test_renders.py
collective/jbot/tests/files/footer.pt
collective/jbot/tests/files/footer2.pt
docs/HISTORY.txt
docs/INSTALL.txt
docs/LICENSE.GPL
docs/LICENSE.txt