Metadata-Version: 1.1
Name: collective.jbot
Version: 1.0a2
Summary: UNKNOWN
Home-page: https://github.com/collective/collective.jbot
Author: Nathan Van Gheem
Author-email: vangheem@gmail.com
License: GPL
Keywords: plone templates customizations
Platform: UNKNOWN
Classifier: Framework :: Plone
Classifier: Programming Language :: Python
